{"data": {"type": "match", "id": "2e851129-46e9-423c-86cb-90610970ff19", "attributes": {"stats": null, "gameMode": "esports-squad-fpp", "titleId": "bluehole-pubg", "tags": null, "seasonState": "progress", "createdAt": "2023-12-01T11:55:40Z", "duration": 1843, "shardId": "tournament", "mapName": "Desert_Main", "isCustomMatch": true, "matchType": ""}, "relationships": {"rosters": {"data": [{"type": "roster", "id": "a740d3b1-008e-4f81-bb61-d5803c2d92e0"}, {"type": "roster", "id": "69c37e77-dd2a-45fc-9618-a620881fe6cb"}, {"type": "roster", "id": "555827e2-6778-4811-9e6c-f457074fd3a8"}, {"type": "roster", "id": "89e4fb96-61fe-4e8e-8501-fa9beb4caabd"}, {"type": "roster", "id": "7992c390-d266-4047-a1a4-acb8f902ef7d"}, {"type": "roster", "id": "49604317-6bb1-4c4a-b89c-2ad655fb98e9"}, {"type": "roster", "id": "b7e5636f-e32e-4602-8e28-6f0ab4ff6395"}, {"type": "roster", "id": "70029c33-dd89-47ce-b78d-bf74a8427d44"}, {"type": "roster", "id": "37ac014e-2112-4078-b2ba-27a79adea919"}, {"type": "roster", "id": "80b6eb0f-4fb3-44eb-8865-69e7ea77b373"}, {"type": "roster", "id": "e14d145b-90be-4086-8dd8-4c421d06f4d6"}, {"type": "roster", "id": "a2e19184-815c-456b-b81c-14f4e61065cc"}, {"type": "roster", "id": "7f2fd76a-32dc-4c0f-8410-e5a6e477da2d"}, {"type": "roster", "id": "e4e079b6-2d61-491e-a63e-9872c841f86b"}, {"type": "roster", "id": "ad105dfa-9048-42cb-a8b2-74b324422092"}, {"type": "roster", "id": "ce4659e2-62ed-453b-873d-23c689f3b861"}]}, "assets": {"data": [{"type": "asset", "id": "1e1c006e-9045-11ee-9ee4-6afa2dbf7a24"}]}}, "links": {"schema": "", "self": "https://api-eks.pubg.com/shards/tournament/matches/2e851129-46e9-423c-86cb-90610970ff19"}}, "included": [{"type": "participant", "id": "84d717ed-3c6c-4e5a-9120-04e4188f80ec", "attributes": {"stats": {"DBNOs": 0, "assists": 0, "boosts": 5, "damageDealt": 248.49649, "deathType": "byplayer", "headshotKills": 0, "heals": 3, "killPlace": 17, "killStreaks": 1, "kills": 1, "longestKill": 2.712396, "name": "CES_HaiSaki", "playerId": "account.dea4fb5a5ef04ca4943915a3b936d2d1", "revives": 0, "rideDistance": 7356.8794, "roadKills": 0, "swimDistance": 0, "teamKills": 0, "timeSurvived": 1724, "vehicleDestroys": 0, "walkDistance": 2136.3608, "weaponsAcquired": 6, "winPlace": 2}, "actor": "", "shardId": "steam"}}, {"type": "participant", "id": "de61a87a-da87-4fdf-b4e8-e4510e860f17", "attributes": {"stats": {"DBNOs": 1, "assists": 0, "boosts": 1, "damageDealt": 144.86032, "deathType": "byplayer", "headshotKills": 0, "heals": 0, "killPlace": 48, "killStreaks": 0, "kills": 0, "longestKill": 0, "name": "PeRo_Aixleft", "playerId": "account.358ae36813c444c2b4ff6b828df69551", "revives": 0, "rideDistance": 1409.5355, "roadKills": 0, "swimDistance": 0, "teamKills": 0, "timeSurvived": 404, "vehicleDestroys": 0, "walkDistance": 512.26917, "weaponsAcquired": 6, "winPlace": 10}, "actor": "", "shardId": "steam"}}, {"type": "participant", "id": "4cee8f34-53c4-4d38-9e1f-936c84a1759b", "attributes": {"actor": "", "shardId": "steam", "stats": {"DBNOs": 0, "assists": 1, "boosts": 4, "damageDealt": 186.27452, "deathType": "byplayer", "headshotKills": 0, "heals": 3, "killPlace": 26, "killStreaks": 1, "kills": 1, "longestKill": 21.85614, "name": "GEN_Esther", "playerId": "account.f19ec7f42ce448fb9fd1be9edcc7f9e4", "revives": 0, "rideDistance": 254.46413, "roadKills": 0, "swimDistance": 0, "teamKills": 0, "timeSurvived": 1327, "vehicleDestroys": 0, "walkDistance": 540.7073, "weaponsAcquired": 5, "winPlace": 8}}}, {"type": "roster", "id": "89e4fb96-61fe-4e8e-8501-fa9beb4caabd", "attributes": {"shardId": "tournament", "stats": {"rank": 2, "teamId": 1}, "won": "false"}, "relationships": {"team": {"data": null}, "participants": {"data": [{"type": "participant", "id": "84d717ed-3c6c-4e5a-9120-04e4188f80ec"}, {"type": "participant", "id": "44369650-334d-4a57-b32c-73a7ec94dc73"}, {"type": "participant", "id": "27b86d22-749d-4f49-b8ea-9af8ebc390ee"}, {"type": "participant", "id": "98c4b121-b90a-4db4-84f5-5d6c96a9df30"}]}}}, {"type": "roster", "id": "49604317-6bb1-4c4a-b89c-2ad655fb98e9", "attributes": {"stats": {"rank": 10, "teamId": 7}, "won": "false", "shardId": "tournament"}, "relationships": {"team": {"data": null}, "participants": {"data": [{"type": "participant", "id": "7dca50e7-8fbf-4d1e-b948-b87f7ae36ff6"}, {"type": "participant", "id": "de61a87a-da87-4fdf-b4e8-e4510e860f17"}, {"type": "participant", "id": "ca5a1fe5-2ba5-4fce-a452-e94e6e92deb4"}, {"type": "participant", "id": "50ba6d92-a540-4f4e-a018-8ad0e2e1f3c6"}]}}}, {"type": "roster", "id": "ad105dfa-9048-42cb-a8b2-74b324422092", "attributes": {"won": "false", "shardId": "tournament", "stats": {"rank": 11, "teamId": 16}}, "relationships": {"team": {"data": null}, "participants": {"data": [{"type": "participant", "id": "3f267085-7183-46bc-9d50-d4400c055990"}, {"type": "participant", "id": "6c59d665-6639-45f8-82a9-64038d5747ea"}, {"type": "participant", "id": "8c1a972b-227d-4eca-8a25-85cd489b9dd7"}, {"type": "participant", "id": "aea097ac-4c81-429b-8c21-af98418f3150"}]}}}, {"type": "participant", "id": "4856b351-0ca8-4f0d-9ded-61df766a6669", "attributes": {"stats": {"DBNOs": 1, "assists": 1, "boosts": 4, "damageDealt": 239.43066, "deathType": "byplayer", "headshotKills": 0, "heals": 3, "killPlace": 27, "killStreaks": 1, "kills": 1, "longestKill": 15.349598, "name": "GEN_DG98", "playerId": "account.b35ab37d7d924b46b51e63d10ae3fa36", "revives": 0, "rideDistance": 4948.0933, "roadKills": 0, "swimDistance": 0, "teamKills": 0, "timeSurvived": 1225, "vehicleDestroys": 0, "walkDistance": 1007.4715, "weaponsAcquired": 3, "winPlace": 8}, "actor": "", "shardId": "steam"}}, {"type": "participant", "id": "fdde16f4-d196-4597-9f28-93a4c2a9fa26", "attributes": {"stats": {"DBNOs": 3, "assists": 1, "boosts": 8, "damageDealt": 463.7246, "deathType": "byplayer", "headshotKills": 1, "heals": 7, "killPlace": 5, "killStreaks": 1, "kills": 3, "longestKill": 230.59784, "name": "DNW_Loki", "playerId": "account.79e030919cac49cda61f9a96d0f38bda", "revives": 1, "rideDistance": 7539.987, "roadKills": 0, "swimDistance": 0, "teamKills": 0, "timeSurvived": 1574, "vehicleDestroys": 0, "walkDistance": 1335.1926, "weaponsAcquired": 6, "winPlace": 6}, "actor": "", "shardId": "steam"}}, {"type": "participant", "id": "349289f4-e17b-4d9f-b9b7-b60c2b3022ae", "attributes": {"stats": {"DBNOs": 0, "assists": 0, "boosts": 1, "damageDealt": 19.918732, "deathType": "byplayer", "headshotKills": 0, "heals": 0, "killPlace": 51, "killStreaks": 0, "kills": 0, "longestKill": 0, "name": "T5_RossitedJR", "playerId": "account.b5a7698dd3974e789b6224b5ff7f1378", "revives": 0, "rideDistance": 1563.0669, "roadKills": 0, "swimDistance": 0, "teamKills": 0, "timeSurvived": 903, "vehicleDestroys": 0, "walkDistance": 836.22656, "weaponsAcquired": 9, "winPlace": 12}, "actor": "", "shardId": "steam"}}, {"type": "participant", "id": "374564c8-efe7-4db6-bbd3-fe14e70f3244", "attributes": {"shardId": "steam", "stats": {"DBNOs": 0, "assists": 0, "boosts": 3, "damageDealt": 67.32375, "deathType": "suicide", "headshotKills": 0, "heals": 8, "killPlace": 57, "killStreaks": 0, "kills": 0, "longestKill": 0, "name": "17_SuJiu", "playerId": "account.183a45369acd46a4888ccb3d0436bdbe", "revives": 0, "rideDistance": 6762.386, "roadKills": 0, "swimDistance": 0, "teamKills": 0, "timeSurvived": 1175, "vehicleDestroys": 1, "walkDistance": 1082.0624, "weaponsAcquired": 6, "winPlace": 14}, "actor": ""}}, {"type": "participant", "id": "9215d4e1-d87a-4885-a091-2eaa12119039", "attributes": {"stats": {"DBNOs": 1, "assists": 0, "boosts": 4, "damageDealt": 262.29532, "deathType": "byplayer", "headshotKills": 0, "heals": 2, "killPlace": 39, "killStreaks": 0, "kills": 0, "longestKill": 0, "name": "SQ_TGLTN", "playerId": "account.95dbe64c2153423da04367cb81e83629", "revives": 0, "rideDistance": 463.77823, "roadKills": 0, "swimDistance": 0, "teamKills": 0, "timeSurvived": 1186, "vehicleDestroys": 0, "walkDistance": 155.5914, "weaponsAcquired": 4, "winPlace": 4}, "actor": "", "shardId": "steam"}}, {"type": "participant", "id": "7dca50e7-8fbf-4d1e-b948-b87f7ae36ff6", "attributes": {"stats": {"DBNOs": 0, "assists": 0, "boosts": 0, "damageDealt": 0, "deathType": "byplayer", "headshotKills": 0, "heals": 0, "killPlace": 49, "killStreaks": 0, "kills": 0, "longestKill": 0, "name": "PeRo_Ming", "playerId": "account.454b06f74f714a9ba5910a4b65691867", "revives": 0, "rideDistance": 1702.266, "roadKills": 0, "swimDistance": 0, "teamKills": 0, "timeSurvived": 378, "vehicleDestroys": 0, "walkDistance": 533.9211, "weaponsAcquired": 3, "winPlace": 10}, "actor": "", "shardId": "steam"}}, {"type": "participant", "id": "e7504bd6-e135-42eb-a1ef-698b7ee1829b", "attributes": {"stats": {"DBNOs": 4, "assists": 1, "boosts": 4, "damageDealt": 494.76315, "deathType": "byplayer", "headshotKills": 0, "heals": 2, "killPlace": 19, "killStreaks": 1, "kills": 1, "longestKill": 251.77611, "name": "SSG_Sharpshot4K", "playerId": "account.1c709f65f8e146bd8760af3bb444eeb4", "revives": 0, "rideDistance": 9493.086, "roadKills": 0, "swimDistance": 0, "teamKills": 0, "timeSurvived": 1825, "vehicleDestroys": 1, "walkDistance": 1349.771, "weaponsAcquired": 9, "winPlace": 3}, "actor": "", "shardId": "steam"}}, {"type": "participant", "id": "7b3301db-3ddc-4c4e-a23f-46f87016fcb8", "attributes": {"shardId": "steam", "stats": {"DBNOs": 0, "assists": 0, "boosts": 1, "damageDealt": 88.59007, "deathType": "byplayer", "headshotKills": 0, "heals": 0, "killPlace": 52, "killStreaks": 0, "kills": 0, "longestKill": 0, "name": "T5_Hatsawat", "playerId": "account.8cac1bff944a49d6bf88661c2e4b04e6", "revives": 0, "rideDistance": 1408.4962, "roadKills": 0, "swimDistance": 0, "teamKills": 0, "timeSurvived": 886, "vehicleDestroys": 0, "walkDistance": 655.1957, "weaponsAcquired": 3, "winPlace": 12}, "actor": ""}}, {"type": "roster", "id": "37ac014e-2112-4078-b2ba-27a79adea919", "attributes": {"stats": {"rank": 8, "teamId": 8}, "won": "false", "shardId": "tournament"}, "relationships": {"team": {"data": null}, "participants": {"data": [{"type": "participant", "id": "862526ea-3ab5-4592-95e1-ffefcb049d46"}, {"type": "participant", "id": "4cee8f34-53c4-4d38-9e1f-936c84a1759b"}, {"type": "participant", "id": "86ffc1da-5870-46f2-b9d7-7524f35919fa"}, {"type": "participant", "id": "4856b351-0ca8-4f0d-9ded-61df766a6669"}]}}}, {"type": "roster", "id": "7f2fd76a-32dc-4c0f-8410-e5a6e477da2d", "attributes": {"stats": {"rank": 12, "teamId": 9}, "won": "false", "shardId": "tournament"}, "relationships": {"team": {"data": null}, "participants": {"data": [{"type": "participant", "id": "342e7ce6-fbe4-4e31-80a8-523df37d1b6d"}, {"type": "participant", "id": "7b3301db-3ddc-4c4e-a23f-46f87016fcb8"}, {"type": "participant", "id": "54d2ee5b-abe8-4475-b18d-74c29c62c8f0"}, {"type": "participant", "id": "349289f4-e17b-4d9f-b9b7-b60c2b3022ae"}]}}}, {"type": "participant", "id": "c2441823-3c60-4156-ba77-491ea336eb83", "attributes": {"shardId": "steam", "stats": {"DBNOs": 3, "assists": 0, "boosts": 8, "damageDealt": 333.40094, "deathType": "byplayer", "headshotKills": 0, "heals": 5, "killPlace": 12, "killStreaks": 1, "kills": 2, "longestKill": 63.982178, "name": "TL_ATongMuu", "playerId": "account.4e0b93ba1c444280b5c852d22ad87cf1", "revives": 2, "rideDistance": 9894.088, "roadKills": 0, "swimDistance": 0, "teamKills": 0, "timeSurvived": 1490, "vehicleDestroys": 1, "walkDistance": 732.64984, "weaponsAcquired": 8, "winPlace": 7}, "actor": ""}}, {"type": "participant", "id": "4b3ee294-5c2c-4053-9870-832721f397c0", "attributes": {"actor": "", "shardId": "steam", "stats": {"DBNOs": 0, "assists": 0, "boosts": 6, "damageDealt": 57.14815, "deathType": "byplayer", "headshotKills": 0, "heals": 2, "killPlace": 55, "killStreaks": 0, "kills": 0, "longestKill": 0, "name": "DAY_Belmoth", "playerId": "account.5140e067558b4d8bbc1ac8d9e2f19fb1", "revives": 0, "rideDistance": 2757.0093, "roadKills": 0, "swimDistance": 0, "teamKills": 0, "timeSurvived": 1172, "vehicleDestroys": 0, "walkDistance": 1472.6722, "weaponsAcquired": 5, "winPlace": 13}}}, {"type": "participant", "id": "50ba6d92-a540-4f4e-a018-8ad0e2e1f3c6", "attributes": {"stats": {"DBNOs": 0, "assists": 0, "boosts": 0, "damageDealt": 0, "deathType": "byplayer", "headshotKills": 0, "heals": 0, "killPlace": 50, "killStreaks": 0, "kills": 0, "longestKill": 0, "name": "PeRo_Cui71", "playerId": "account.c596e9d2c25c4e41872285a292a14b4d", "revives": 0, "rideDistance": 523.29834, "roadKills": 0, "swimDistance": 0, "teamKills": 0, "timeSurvived": 145, "vehicleDestroys": 0, "walkDistance": 35.12306, "weaponsAcquired": 1, "winPlace": 10}, "actor": "", "shardId": "steam"}}, {"type": "participant", "id": "b990a1f5-91e4-45f9-9b84-d9c93dafb713", "attributes": {"stats": {"DBNOs": 0, "assists": 1, "boosts": 2, "damageDealt": 77.4, "deathType": "byplayer", "headshotKills": 0, "heals": 1, "killPlace": 64, "killStreaks": 0, "kills": 0, "longestKill": 0, "name": "V7_Tosi", "playerId": "account.8c4b945d989b4662ad4f00a3273fb027", "revives": 0, "rideDistance": 0, "roadKills": 0, "swimDistance": 0, "teamKills": 0, "timeSurvived": 948, "vehicleDestroys": 0, "walkDistance": 54.572685, "weaponsAcquired": 8, "winPlace": 16}, "actor": "", "shardId": "steam"}}, {"type": "participant", "id": "6ca2468e-e53c-4aa6-9e62-e659f9e4f0b5", "attributes": {"stats": {"DBNOs": 1, "assists": 1, "boosts": 4, "damageDealt": 291.94342, "deathType": "byplayer", "headshotKills": 1, "heals": 4, "killPlace": 25, "killStreaks": 1, "kills": 1, "longestKill": 9.265134, "name": "TL_Jiaoyang", "playerId": "account.b1eef743995a4f89870633b2edb17538", "revives": 4, "rideDistance": 9321.505, "roadKills": 0, "swimDistance": 0, "teamKills": 0, "timeSurvived": 1490, "vehicleDestroys": 0, "walkDistance": 901.4286, "weaponsAcquired": 5, "winPlace": 7}, "actor": "", "shardId": "steam"}}, {"type": "participant", "id": "cd92f98c-1836-42e6-9e98-c77fbef38555", "attributes": {"stats": {"DBNOs": 1, "assists": 1, "boosts": 6, "damageDealt": 231.9618, "deathType": "byplayer", "headshotKills": 0, "heals": 1, "killPlace": 18, "killStreaks": 1, "kills": 1, "longestKill": 190.05, "name": "SSG_PaG3", "playerId": "account.111c752c6e5f43f68b986f0725767fa6", "revives": 0, "rideDistance": 9985.624, "roadKills": 0, "swimDistance": 0, "teamKills": 0, "timeSurvived": 1825, "vehicleDestroys": 0, "walkDistance": 1446.0242, "weaponsAcquired": 4, "winPlace": 3}, "actor": "", "shardId": "steam"}}, {"type": "participant", "id": "bcc4b1a5-9189-4d9f-82d7-cf8a2e7ea23f", "attributes": {"stats": {"DBNOs": 2, "assists": 0, "boosts": 12, "damageDealt": 380.07095, "deathType": "byplayer", "headshotKills": 0, "heals": 1, "killPlace": 20, "killStreaks": 1, "kills": 1, "longestKill": 537.5734, "name": "SSG_PiXeL1K", "playerId": "account.447fdbc9247d4b4baa399d14721d4636", "revives": 0, "rideDistance": 9221.557, "roadKills": 0, "swimDistance": 0, "teamKills": 0, "timeSurvived": 1825, "vehicleDestroys": 0, "walkDistance": 1641.1879, "weaponsAcquired": 6, "winPlace": 3}, "actor": "", "shardId": "steam"}}, {"type": "participant", "id": "3f267085-7183-46bc-9d50-d4400c055990", "attributes": {"actor": "", "shardId": "steam", "stats": {"DBNOs": 2, "assists": 1, "boosts": 6, "damageDealt": 342.32697, "deathType": "byplayer", "headshotKills": 0, "heals": 6, "killPlace": 3, "killStreaks": 1, "kills": 4, "longestKill": 171.30273, "name": "TWIS_BatulinS", "playerId": "account.fff088a8a2b64fbf86cf283cddc1e706", "revives": 0, "rideDistance": 3250.2776, "roadKills": 0, "swimDistance": 0, "teamKills": 0, "timeSurvived": 1236, "vehicleDestroys": 0, "walkDistance": 1020.9794, "weaponsAcquired": 7, "winPlace": 11}}}, {"type": "participant", "id": "ca90d0b0-13bf-438b-9668-5946a3a4b637", "attributes": {"actor": "", "shardId": "steam", "stats": {"DBNOs": 3, "assists": 0, "boosts": 7, "damageDealt": 447.87576, "deathType": "byplayer", "headshotKills": 0, "heals": 3, "killPlace": 2, "killStreaks": 2, "kills": 4, "longestKill": 566.2658, "name": "SQ_Kickstart", "playerId": "account.f95d11cb515746a68b59630103a4cede", "revives": 4, "rideDistance": 476.93933, "roadKills": 0, "swimDistance": 0, "teamKills": 0, "timeSurvived": 1752, "vehicleDestroys": 1, "walkDistance": 508.95374, "weaponsAcquired": 8, "winPlace": 4}}}, {"type": "participant", "id": "f8de9cbf-3540-4028-8a12-197139fe0ea4", "attributes": {"stats": {"DBNOs": 0, "assists": 0, "boosts": 2, "damageDealt": 24.884998, "deathType": "byplayer", "headshotKills": 0, "heals": 1, "killPlace": 54, "killStreaks": 0, "kills": 0, "longestKill": 0, "name": "DAY_Nourinz", "playerId": "account.b584be6230df4b2c90e7e86917e94127", "revives": 0, "rideDistance": 2947.0222, "roadKills": 0, "swimDistance": 0, "teamKills": 0, "timeSurvived": 1183, "vehicleDestroys": 0, "walkDistance": 1090.7837, "weaponsAcquired": 5, "winPlace": 13}, "actor": "", "shardId": "steam"}}, {"type": "participant", "id": "e2a8bb8c-cb51-4cdf-bff4-b74c23d2ee23", "attributes": {"stats": {"DBNOs": 1, "assists": 0, "boosts": 4, "damageDealt": 234.31879, "deathType": "byplayer", "headshotKills": 0, "heals": 5, "killPlace": 15, "killStreaks": 1, "kills": 2, "longestKill": 184.25967, "name": "Tian_LinShu23", "playerId": "account.6558090c205042f997ef1afa894b34e8", "revives": 0, "rideDistance": 4530.9805, "roadKills": 0, "swimDistance": 0, "teamKills": 0, "timeSurvived": 1015, "vehicleDestroys": 0, "walkDistance": 815.8682, "weaponsAcquired": 6, "winPlace": 15}, "actor": "", "shardId": "steam"}}, {"type": "participant", "id": "862526ea-3ab5-4592-95e1-ffefcb049d46", "attributes": {"stats": {"DBNOs": 0, "assists": 0, "boosts": 4, "damageDealt": 0, "deathType": "byplayer", "headshotKills": 0, "heals": 5, "killPlace": 44, "killStreaks": 0, "kills": 0, "longestKill": 0, "name": "GEN_Seongjang", "playerId": "account.5fc60d0f31f0433fb4b58a48e6fc4ef4", "revives": 0, "rideDistance": 2312.9722, "roadKills": 0, "swimDistance": 0, "teamKills": 0, "timeSurvived": 945, "vehicleDestroys": 0, "walkDistance": 391.29333, "weaponsAcquired": 4, "winPlace": 8}, "actor": "", "shardId": "steam"}}, {"type": "participant", "id": "6669bd76-3a1a-495d-9c4c-1b5e6859a8af", "attributes": {"stats": {"DBNOs": 0, "assists": 0, "boosts": 8, "damageDealt": 190.86209, "deathType": "byplayer", "headshotKills": 0, "heals": 2, "killPlace": 38, "killStreaks": 0, "kills": 0, "longestKill": 0, "name": "SSG_Roth", "playerId": "account.bbd62c6ab18442608c0b0a8d039de006", "revives": 0, "rideDistance": 10019.6, "roadKills": 0, "swimDistance": 0, "teamKills": 0, "timeSurvived": 1825, "vehicleDestroys": 0, "walkDistance": 1150.2446, "weaponsAcquired": 8, "winPlace": 3}, "actor": "", "shardId": "steam"}}, {"type": "participant", "id": "54caae07-bd13-4657-b1de-6088c4888737", "attributes": {"stats": {"DBNOs": 1, "assists": 0, "boosts": 2, "damageDealt": 74.649155, "deathType": "byplayer", "headshotKills": 0, "heals": 0, "killPlace": 24, "killStreaks": 1, "kills": 1, "longestKill": 81.38592, "name": "DNW_Salute", "playerId": "account.2375c9d38a6a4fe9af48f83089aa6d43", "revives": 0, "rideDistance": 8321.33, "roadKills": 0, "swimDistance": 0, "teamKills": 0, "timeSurvived": 924, "vehicleDestroys": 0, "walkDistance": 659.54944, "weaponsAcquired": 7, "winPlace": 6}, "actor": "", "shardId": "steam"}}, {"type": "participant", "id": "342e7ce6-fbe4-4e31-80a8-523df37d1b6d", "attributes": {"actor": "", "shardId": "steam", "stats": {"DBNOs": 1, "assists": 0, "boosts": 1, "damageDealt": 200.82515, "deathType": "byplayer", "headshotKills": 0, "heals": 0, "killPlace": 32, "killStreaks": 1, "kills": 1, "longestKill": 19.611837, "name": "T5_Thanad0l", "playerId": "account.08ae687f7dff4a438dcd7c8d56ac6e11", "revives": 1, "rideDistance": 1350.707, "roadKills": 0, "swimDistance": 0, "teamKills": 0, "timeSurvived": 1121, "vehicleDestroys": 0, "walkDistance": 1210.3293, "weaponsAcquired": 4, "winPlace": 12}}}, {"type": "roster", "id": "a2e19184-815c-456b-b81c-14f4e61065cc", "attributes": {"stats": {"rank": 6, "teamId": 10}, "won": "false", "shardId": "tournament"}, "relationships": {"team": {"data": null}, "participants": {"data": [{"type": "participant", "id": "fdde16f4-d196-4597-9f28-93a4c2a9fa26"}, {"type": "participant", "id": "54caae07-bd13-4657-b1de-6088c4888737"}, {"type": "participant", "id": "5fe2cfd5-f0f8-4e12-8a4e-55b02741544b"}, {"type": "participant", "id": "1ea6b6c2-5d35-4c93-880f-08c75ec3d4cd"}]}}}, {"type": "participant", "id": "47c07157-d8da-4a4e-bd32-0278b3f08406", "attributes": {"stats": {"DBNOs": 0, "assists": 0, "boosts": 1, "damageDealt": 49.99633, "deathType": "byplayer", "headshotKills": 0, "heals": 1, "killPlace": 65, "killStreaks": 0, "kills": 0, "longestKill": 0, "name": "V7_Glaz", "playerId": "account.ca532dd9610c41d6abb5718673a13e0d", "revives": 0, "rideDistance": 0, "roadKills": 0, "swimDistance": 0, "teamKills": 0, "timeSurvived": 948, "vehicleDestroys": 0, "walkDistance": 9.97302, "weaponsAcquired": 8, "winPlace": 16}, "actor": "", "shardId": "steam"}}, {"type": "participant", "id": "86ffc1da-5870-46f2-b9d7-7524f35919fa", "attributes": {"stats": {"DBNOs": 1, "assists": 0, "boosts": 3, "damageDealt": 151.03586, "deathType": "byplayer", "headshotKills": 0, "heals": 0, "killPlace": 28, "killStreaks": 1, "kills": 1, "longestKill": 76.43674, "name": "GEN_Pio", "playerId": "account.2f3338b89f2c473d88f5a0d3886371f3", "revives": 0, "rideDistance": 1931.1616, "roadKills": 0, "swimDistance": 0, "teamKills": 0, "timeSurvived": 906, "vehicleDestroys": 0, "walkDistance": 610.82477, "weaponsAcquired": 5, "winPlace": 8}, "actor": "", "shardId": "steam"}}, {"type": "participant", "id": "21a4836a-bddd-4506-bec9-b56d78f36875", "attributes": {"actor": "", "shardId": "steam", "stats": {"DBNOs": 3, "assists": 2, "boosts": 7, "damageDealt": 782.7607, "deathType": "alive", "headshotKills": 2, "heals": 3, "killPlace": 1, "killStreaks": 2, "kills": 5, "longestKill": 207.7343, "name": "NH_CC108", "playerId": "account.5372851f3e9545b78d4d8a70b6ea605a", "revives": 1, "rideDistance": 8369.527, "roadKills": 0, "swimDistance": 0, "teamKills": 0, "timeSurvived": 1843, "vehicleDestroys": 0, "walkDistance": 1370.0483, "weaponsAcquired": 4, "winPlace": 1}}}, {"type": "roster", "id": "a740d3b1-008e-4f81-bb61-d5803c2d92e0", "attributes": {"stats": {"rank": 7, "teamId": 4}, "won": "false", "shardId": "tournament"}, "relationships": {"team": {"data": null}, "participants": {"data": [{"type": "participant", "id": "6ca2468e-e53c-4aa6-9e62-e659f9e4f0b5"}, {"type": "participant", "id": "c2441823-3c60-4156-ba77-491ea336eb83"}, {"type": "participant", "id": "f6f26f70-26df-4777-829c-0e839e96ab80"}, {"type": "participant", "id": "f6347359-4996-4104-9f40-6ee882489437"}]}}}, {"type": "participant", "id": "9b800055-0d02-4620-8250-216c823f646e", "attributes": {"stats": {"DBNOs": 0, "assists": 0, "boosts": 4, "damageDealt": 0, "deathType": "byplayer", "headshotKills": 0, "heals": 3, "killPlace": 62, "killStreaks": 0, "kills": 0, "longestKill": 0, "name": "Tian_77owo", "playerId": "account.6d44884704e24010ad2bb7ebb9055fee", "revives": 0, "rideDistance": 4118.057, "roadKills": 0, "swimDistance": 0, "teamKills": 0, "timeSurvived": 955, "vehicleDestroys": 0, "walkDistance": 577.02356, "weaponsAcquired": 2, "winPlace": 15}, "actor": "", "shardId": "steam"}}, {"type": "participant", "id": "c8c1a462-e740-46e5-bb0d-8c2451d5802d", "attributes": {"stats": {"DBNOs": 0, "assists": 0, "boosts": 1, "damageDealt": 17.4123, "deathType": "byplayer", "headshotKills": 0, "heals": 0, "killPlace": 66, "killStreaks": 0, "kills": 0, "longestKill": 0, "name": "V7_Gyumin", "playerId": "account.95041c39b2d14a088087b417af03c04f", "revives": 0, "rideDistance": 0, "roadKills": 0, "swimDistance": 0, "teamKills": 0, "timeSurvived": 916, "vehicleDestroys": 0, "walkDistance": 1.8220352, "weaponsAcquired": 4, "winPlace": 16}, "actor": "", "shardId": "steam"}}, {"type": "participant", "id": "5fe2cfd5-f0f8-4e12-8a4e-55b02741544b", "attributes": {"stats": {"DBNOs": 1, "assists": 0, "boosts": 2, "damageDealt": 214.10538, "deathType": "byplayer", "headshotKills": 0, "heals": 0, "killPlace": 41, "killStreaks": 0, "kills": 0, "longestKill": 0, "name": "DNW_Inonix", "playerId": "account.3a5ab7f1df8444e7b91e666beb7d3a02", "revives": 0, "rideDistance": 7015.9023, "roadKills": 0, "swimDistance": 0, "teamKills": 0, "timeSurvived": 943, "vehicleDestroys": 0, "walkDistance": 611.0257, "weaponsAcquired": 3, "winPlace": 6}, "actor": "", "shardId": "steam"}}, {"type": "participant", "id": "09a46039-c0d4-4923-a8be-06abbaccb7e7", "attributes": {"stats": {"DBNOs": 0, "assists": 0, "boosts": 6, "damageDealt": 105.07563, "deathType": "byplayer", "headshotKills": 0, "heals": 0, "killPlace": 59, "killStreaks": 0, "kills": 0, "longestKill": 0, "name": "17_Xbei", "playerId": "account.7b13f44c9ecb439b8e906362d974afb8", "revives": 0, "rideDistance": 7003.6123, "roadKills": 0, "swimDistance": 0, "teamKills": 0, "timeSurvived": 1133, "vehicleDestroys": 0, "walkDistance": 1046.9877, "weaponsAcquired": 6, "winPlace": 14}, "actor": "", "shardId": "steam"}}, {"type": "roster", "id": "e14d145b-90be-4086-8dd8-4c421d06f4d6", "attributes": {"stats": {"rank": 3, "teamId": 5}, "won": "false", "shardId": "tournament"}, "relationships": {"team": {"data": null}, "participants": {"data": [{"type": "participant", "id": "6669bd76-3a1a-495d-9c4c-1b5e6859a8af"}, {"type": "participant", "id": "cd92f98c-1836-42e6-9e98-c77fbef38555"}, {"type": "participant", "id": "bcc4b1a5-9189-4d9f-82d7-cf8a2e7ea23f"}, {"type": "participant", "id": "e7504bd6-e135-42eb-a1ef-698b7ee1829b"}]}}}, {"type": "participant", "id": "7c235718-c0e5-4427-b048-fc42b4b4d751", "attributes": {"stats": {"DBNOs": 1, "assists": 0, "boosts": 2, "damageDealt": 100, "deathType": "byplayer", "headshotKills": 0, "heals": 2, "killPlace": 33, "killStreaks": 1, "kills": 1, "longestKill": 8.299948, "name": "V7_Heaven", "playerId": "account.766148a3fa8f41ab87183e07e74d4a6e", "revives": 0, "rideDistance": 0, "roadKills": 0, "swimDistance": 0, "teamKills": 0, "timeSurvived": 928, "vehicleDestroys": 0, "walkDistance": 1.5124593, "weaponsAcquired": 9, "winPlace": 16}, "actor": "", "shardId": "steam"}}, {"type": "participant", "id": "addaefbd-96f0-4282-9363-fbc0c4c4fc07", "attributes": {"stats": {"DBNOs": 2, "assists": 2, "boosts": 9, "damageDealt": 478.67368, "deathType": "alive", "headshotKills": 1, "heals": 3, "killPlace": 7, "killStreaks": 1, "kills": 2, "longestKill": 30.133945, "name": "NH_Dec12th", "playerId": "account.77be07e20d244421bf882fea6c1e9926", "revives": 0, "rideDistance": 8515.336, "roadKills": 0, "swimDistance": 0, "teamKills": 0, "timeSurvived": 1843, "vehicleDestroys": 0, "walkDistance": 1767.6663, "weaponsAcquired": 7, "winPlace": 1}, "actor": "", "shardId": "steam"}}, {"type": "roster", "id": "b7e5636f-e32e-4602-8e28-6f0ab4ff6395", "attributes": {"stats": {"rank": 16, "teamId": 15}, "won": "false", "shardId": "tournament"}, "relationships": {"team": {"data": null}, "participants": {"data": [{"type": "participant", "id": "b990a1f5-91e4-45f9-9b84-d9c93dafb713"}, {"type": "participant", "id": "47c07157-d8da-4a4e-bd32-0278b3f08406"}, {"type": "participant", "id": "7c235718-c0e5-4427-b048-fc42b4b4d751"}, {"type": "participant", "id": "c8c1a462-e740-46e5-bb0d-8c2451d5802d"}]}}}, {"type": "participant", "id": "f6347359-4996-4104-9f40-6ee882489437", "attributes": {"stats": {"DBNOs": 1, "assists": 0, "boosts": 5, "damageDealt": 148.93036, "deathType": "byplayer", "headshotKills": 0, "heals": 1, "killPlace": 43, "killStreaks": 0, "kills": 0, "longestKill": 0, "name": "TL_Shen", "playerId": "account.2f6ccd93ce9645a096546f78a4383c66", "revives": 0, "rideDistance": 10086.321, "roadKills": 0, "swimDistance": 0, "teamKills": 0, "timeSurvived": 1099, "vehicleDestroys": 0, "walkDistance": 681.2265, "weaponsAcquired": 8, "winPlace": 7}, "actor": "", "shardId": "steam"}}, {"type": "participant", "id": "af531159-2e74-449c-bcde-138827554b3c", "attributes": {"stats": {"DBNOs": 3, "assists": 2, "boosts": 7, "damageDealt": 569.9231, "deathType": "suicide", "headshotKills": 0, "heals": 6, "killPlace": 9, "killStreaks": 2, "kills": 2, "longestKill": 13.718009, "name": "SQ_Shrimzy", "playerId": "account.12e2a0dc0dbb4bd882dbf40df0d564f4", "revives": 0, "rideDistance": 456.10724, "roadKills": 0, "swimDistance": 0, "teamKills": 0, "timeSurvived": 1741, "vehicleDestroys": 0, "walkDistance": 471.61945, "weaponsAcquired": 10, "winPlace": 4}, "actor": "", "shardId": "steam"}}, {"type": "participant", "id": "372eac2a-c41d-4c8f-a676-75df69f13a88", "attributes": {"actor": "", "shardId": "steam", "stats": {"DBNOs": 0, "assists": 0, "boosts": 4, "damageDealt": 93.97942, "deathType": "byplayer", "headshotKills": 0, "heals": 0, "killPlace": 63, "killStreaks": 0, "kills": 0, "longestKill": 0, "name": "Tian_Zyy", "playerId": "account.e17ede0921cf47269ce62560299ec387", "revives": 0, "rideDistance": 4415.431, "roadKills": 0, "swimDistance": 0, "teamKills": 0, "timeSurvived": 852, "vehicleDestroys": 0, "walkDistance": 720.1292, "weaponsAcquired": 3, "winPlace": 15}}}, {"type": "participant", "id": "f2adef90-9f8f-4884-8f53-bedf33a29c87", "attributes": {"stats": {"DBNOs": 0, "assists": 0, "boosts": 2, "damageDealt": 87.546036, "deathType": "byplayer", "headshotKills": 0, "heals": 1, "killPlace": 45, "killStreaks": 0, "kills": 0, "longestKill": 0, "name": "LG_Fludd", "playerId": "account.724b0358952440579ebc7f3391bb49ad", "revives": 0, "rideDistance": 3952.9275, "roadKills": 0, "swimDistance": 0, "teamKills": 0, "timeSurvived": 1077, "vehicleDestroys": 1, "walkDistance": 655.6295, "weaponsAcquired": 4, "winPlace": 9}, "actor": "", "shardId": "steam"}}, {"type": "participant", "id": "4fef1613-a8e7-42e9-9921-e08283144906", "attributes": {"stats": {"DBNOs": 0, "assists": 0, "boosts": 1, "damageDealt": 48.120796, "deathType": "byplayer", "headshotKills": 0, "heals": 1, "killPlace": 40, "killStreaks": 0, "kills": 0, "longestKill": 0, "name": "SQ_hwinn", "playerId": "account.cadc0e574c244d1db903c2e84d694836", "revives": 0, "rideDistance": 2583.6477, "roadKills": 0, "swimDistance": 0, "teamKills": 0, "timeSurvived": 940, "vehicleDestroys": 0, "walkDistance": 1248.8757, "weaponsAcquired": 4, "winPlace": 4}, "actor": "", "shardId": "steam"}}, {"type": "participant", "id": "58e81669-5b88-41bf-a8ba-c70ccb285a19", "attributes": {"shardId": "steam", "stats": {"DBNOs": 0, "assists": 0, "boosts": 4, "damageDealt": 21.432608, "deathType": "byplayer", "headshotKills": 0, "heals": 0, "killPlace": 47, "killStreaks": 0, "kills": 0, "longestKill": 0, "name": "LG_M1ME", "playerId": "account.d88badd38c6b457ba17f72fd825b3dbb", "revives": 0, "rideDistance": 2884.6138, "roadKills": 0, "swimDistance": 0, "teamKills": 0, "timeSurvived": 1066, "vehicleDestroys": 0, "walkDistance": 2227.3772, "weaponsAcquired": 5, "winPlace": 9}, "actor": ""}}, {"type": "participant", "id": "1ea6b6c2-5d35-4c93-880f-08c75ec3d4cd", "attributes": {"stats": {"DBNOs": 1, "assists": 1, "boosts": 8, "damageDealt": 336.69537, "deathType": "byplayer", "headshotKills": 1, "heals": 7, "killPlace": 11, "killStreaks": 1, "kills": 2, "longestKill": 58.10915, "name": "DNW_seoul", "playerId": "account.80312051ca20415dbf0a35c910154a82", "revives": 1, "rideDistance": 7185.261, "roadKills": 0, "swimDistance": 0, "teamKills": 0, "timeSurvived": 1559, "vehicleDestroys": 0, "walkDistance": 1287.9557, "weaponsAcquired": 7, "winPlace": 6}, "actor": "", "shardId": "steam"}}, {"type": "participant", "id": "6c59d665-6639-45f8-82a9-64038d5747ea", "attributes": {"actor": "", "shardId": "steam", "stats": {"DBNOs": 2, "assists": 1, "boosts": 2, "damageDealt": 139.1895, "deathType": "byplayer", "headshotKills": 0, "heals": 3, "killPlace": 30, "killStreaks": 1, "kills": 1, "longestKill": 14.145957, "name": "TWIS_Lu", "playerId": "account.615d20582bcc4d5cb5818922caab2f22", "revives": 1, "rideDistance": 0, "roadKills": 0, "swimDistance": 0, "teamKills": 0, "timeSurvived": 1236, "vehicleDestroys": 0, "walkDistance": 232.08482, "weaponsAcquired": 3, "winPlace": 11}}}, {"type": "participant", "id": "532a9cf0-3078-4293-adbe-69928a1fe458", "attributes": {"stats": {"DBNOs": 0, "assists": 0, "boosts": 6, "damageDealt": 106.17975, "deathType": "byplayer", "headshotKills": 0, "heals": 4, "killPlace": 58, "killStreaks": 0, "kills": 0, "longestKill": 0, "name": "17_Lilghost", "playerId": "account.711dd801ef9940029675f49595c989a9", "revives": 0, "rideDistance": 7906.6855, "roadKills": 0, "swimDistance": 0, "teamKills": 0, "timeSurvived": 1175, "vehicleDestroys": 0, "walkDistance": 1136.0518, "weaponsAcquired": 3, "winPlace": 14}, "actor": "", "shardId": "steam"}}, {"type": "roster", "id": "80b6eb0f-4fb3-44eb-8865-69e7ea77b373", "attributes": {"won": "true", "shardId": "tournament", "stats": {"rank": 1, "teamId": 6}}, "relationships": {"team": {"data": null}, "participants": {"data": [{"type": "participant", "id": "e65e95ab-a5bd-4a98-9486-ba8550fb8ed9"}, {"type": "participant", "id": "21a4836a-bddd-4506-bec9-b56d78f36875"}, {"type": "participant", "id": "47c47cc3-9914-4b48-a758-7330b5dc8e82"}, {"type": "participant", "id": "addaefbd-96f0-4282-9363-fbc0c4c4fc07"}]}}}, {"type": "participant", "id": "44369650-334d-4a57-b32c-73a7ec94dc73", "attributes": {"stats": {"DBNOs": 3, "assists": 1, "boosts": 6, "damageDealt": 852.5559, "deathType": "byplayer", "headshotKills": 0, "heals": 4, "killPlace": 4, "killStreaks": 1, "kills": 3, "longestKill": 65.07097, "name": "CES_Himass", "playerId": "account.c2762cc306ef4dd59c67f1866bfb69a1", "revives": 1, "rideDistance": 9098.208, "roadKills": 0, "swimDistance": 0, "teamKills": 0, "timeSurvived": 1843, "vehicleDestroys": 2, "walkDistance": 1491.5062, "weaponsAcquired": 7, "winPlace": 2}, "actor": "", "shardId": "steam"}}, {"type": "participant", "id": "47c47cc3-9914-4b48-a758-7330b5dc8e82", "attributes": {"stats": {"DBNOs": 2, "assists": 1, "boosts": 8, "damageDealt": 608.59143, "deathType": "alive", "headshotKills": 1, "heals": 3, "killPlace": 8, "killStreaks": 1, "kills": 2, "longestKill": 137.92078, "name": "NH_MMing", "playerId": "account.16db8a07e53e459fad9c89a84a67a42a", "revives": 0, "rideDistance": 8021.279, "roadKills": 0, "swimDistance": 0, "teamKills": 0, "timeSurvived": 1843, "vehicleDestroys": 0, "walkDistance": 1906.7906, "weaponsAcquired": 4, "winPlace": 1}, "actor": "", "shardId": "steam"}}, {"type": "participant", "id": "8c1a972b-227d-4eca-8a25-85cd489b9dd7", "attributes": {"actor": "", "shardId": "steam", "stats": {"DBNOs": 2, "assists": 4, "boosts": 2, "damageDealt": 580.15216, "deathType": "byplayer", "headshotKills": 0, "heals": 4, "killPlace": 13, "killStreaks": 1, "kills": 2, "longestKill": 62.655323, "name": "TWIS_Perfect1ks", "playerId": "account.6d5d4e01468f4920846978b6dd5f2558", "revives": 0, "rideDistance": 3820.6038, "roadKills": 0, "swimDistance": 0, "teamKills": 0, "timeSurvived": 1236, "vehicleDestroys": 1, "walkDistance": 1401.5707, "weaponsAcquired": 7, "winPlace": 11}}}, {"type": "participant", "id": "aea097ac-4c81-429b-8c21-af98418f3150", "attributes": {"stats": {"DBNOs": 1, "assists": 1, "boosts": 7, "damageDealt": 197.06242, "deathType": "byplayer", "headshotKills": 0, "heals": 6, "killPlace": 31, "killStreaks": 1, "kills": 1, "longestKill": 11.360363, "name": "TWIS_spyrro", "playerId": "account.e6f018911cea4b18a6b890e99446dac7", "revives": 0, "rideDistance": 4480.825, "roadKills": 0, "swimDistance": 0, "teamKills": 0, "timeSurvived": 1229, "vehicleDestroys": 0, "walkDistance": 1228.4822, "weaponsAcquired": 3, "winPlace": 11}, "actor": "", "shardId": "steam"}}, {"type": "participant", "id": "f6f26f70-26df-4777-829c-0e839e96ab80", "attributes": {"stats": {"DBNOs": 0, "assists": 1, "boosts": 5, "damageDealt": 18.66375, "deathType": "byplayer", "headshotKills": 0, "heals": 2, "killPlace": 42, "killStreaks": 0, "kills": 0, "longestKill": 0, "name": "TL_Lzqq", "playerId": "account.1cfab29a77634c5487aeb6467c2200cb", "revives": 0, "rideDistance": 10680.474, "roadKills": 0, "swimDistance": 0, "teamKills": 0, "timeSurvived": 1192, "vehicleDestroys": 0, "walkDistance": 561.6913, "weaponsAcquired": 5, "winPlace": 7}, "actor": "", "shardId": "steam"}}, {"type": "participant", "id": "74266520-0fde-4917-9f58-2dbe148dc691", "attributes": {"stats": {"DBNOs": 0, "assists": 0, "boosts": 2, "damageDealt": 0, "deathType": "byplayer", "headshotKills": 0, "heals": 3, "killPlace": 56, "killStreaks": 0, "kills": 0, "longestKill": 0, "name": "DAY_PuuChiwz", "playerId": "account.8d67f07455aa483eb4bbad346dfe6707", "revives": 0, "rideDistance": 2922.7556, "roadKills": 0, "swimDistance": 0, "teamKills": 0, "timeSurvived": 1157, "vehicleDestroys": 0, "walkDistance": 1111.7957, "weaponsAcquired": 5, "winPlace": 13}, "actor": "", "shardId": "steam"}}, {"type": "participant", "id": "370190bf-6c89-44b1-91ec-68354ede2ae1", "attributes": {"stats": {"DBNOs": 0, "assists": 0, "boosts": 3, "damageDealt": 158.62503, "deathType": "byplayer", "headshotKills": 0, "heals": 2, "killPlace": 53, "killStreaks": 0, "kills": 0, "longestKill": 0, "name": "DAY_Flash", "playerId": "account.a12bbe8283bd43768ae28f76f86a465d", "revives": 0, "rideDistance": 2865.74, "roadKills": 0, "swimDistance": 0, "teamKills": 0, "timeSurvived": 1184, "vehicleDestroys": 0, "walkDistance": 1663.1385, "weaponsAcquired": 6, "winPlace": 13}, "actor": "", "shardId": "steam"}}, {"type": "participant", "id": "98c4b121-b90a-4db4-84f5-5d6c96a9df30", "attributes": {"actor": "", "shardId": "steam", "stats": {"DBNOs": 1, "assists": 1, "boosts": 2, "damageDealt": 174.48485, "deathType": "byplayer", "headshotKills": 0, "heals": 0, "killPlace": 37, "killStreaks": 0, "kills": 0, "longestKill": 0, "name": "CES_Taikonn", "playerId": "account.7d13843e20ae458393aa5eefcad46256", "revives": 0, "rideDistance": 8363.36, "roadKills": 0, "swimDistance": 0, "teamKills": 0, "timeSurvived": 1545, "vehicleDestroys": 0, "walkDistance": 1166.4938, "weaponsAcquired": 4, "winPlace": 2}}}, {"type": "participant", "id": "ca5a1fe5-2ba5-4fce-a452-e94e6e92deb4", "attributes": {"shardId": "steam", "stats": {"DBNOs": 1, "assists": 0, "boosts": 5, "damageDealt": 290.896, "deathType": "byplayer", "headshotKills": 0, "heals": 4, "killPlace": 29, "killStreaks": 1, "kills": 1, "longestKill": 62.44493, "name": "PeRo_Summer", "playerId": "account.d647ce8c37054618ad0b75bf5de86ccb", "revives": 0, "rideDistance": 1244.2047, "roadKills": 0, "swimDistance": 0, "teamKills": 0, "timeSurvived": 1257, "vehicleDestroys": 0, "walkDistance": 1929.5442, "weaponsAcquired": 6, "winPlace": 10}, "actor": ""}}, {"type": "participant", "id": "f2ded8eb-7500-4123-b5b2-f326fe233a2e", "attributes": {"stats": {"DBNOs": 1, "assists": 0, "boosts": 4, "damageDealt": 274.1936, "deathType": "byplayer", "headshotKills": 1, "heals": 5, "killPlace": 6, "killStreaks": 1, "kills": 3, "longestKill": 132.62784, "name": "LG_Snakers", "playerId": "account.2efa55271d4842f98b1fd811dca09440", "revives": 0, "rideDistance": 3270.4746, "roadKills": 0, "swimDistance": 0, "teamKills": 0, "timeSurvived": 1308, "vehicleDestroys": 0, "walkDistance": 1451.423, "weaponsAcquired": 4, "winPlace": 9}, "actor": "", "shardId": "steam"}}, {"type": "participant", "id": "54d2ee5b-abe8-4475-b18d-74c29c62c8f0", "attributes": {"actor": "", "shardId": "steam", "stats": {"DBNOs": 2, "assists": 0, "boosts": 3, "damageDealt": 491.8652, "deathType": "byplayer", "headshotKills": 0, "heals": 6, "killPlace": 14, "killStreaks": 1, "kills": 2, "longestKill": 7.548627, "name": "T5_Pathompong", "playerId": "account.f95fd6b654a5401e8b0acac768063f35", "revives": 0, "rideDistance": 2101.388, "roadKills": 0, "swimDistance": 0, "teamKills": 0, "timeSurvived": 1212, "vehicleDestroys": 0, "walkDistance": 1214.0973, "weaponsAcquired": 9, "winPlace": 12}}}, {"type": "participant", "id": "ffa5bea1-2037-491c-9dba-94d1ef42b361", "attributes": {"stats": {"DBNOs": 1, "assists": 1, "boosts": 9, "damageDealt": 257.88824, "deathType": "byplayer", "headshotKills": 1, "heals": 6, "killPlace": 21, "killStreaks": 1, "kills": 1, "longestKill": 4.5699477, "name": "FaZe_Gustav", "playerId": "account.89fd42f81d324253b581b8cf8b004ac4", "revives": 2, "rideDistance": 4090.577, "roadKills": 0, "swimDistance": 0, "teamKills": 0, "timeSurvived": 1632, "vehicleDestroys": 2, "walkDistance": 1774.1217, "weaponsAcquired": 8, "winPlace": 5}, "actor": "", "shardId": "steam"}}, {"type": "participant", "id": "ea9c56f7-092c-4fab-aa63-a17988879cdb", "attributes": {"stats": {"DBNOs": 0, "assists": 0, "boosts": 4, "damageDealt": 61.44683, "deathType": "byplayer", "headshotKills": 0, "heals": 0, "killPlace": 60, "killStreaks": 0, "kills": 0, "longestKill": 0, "name": "17_xwudd", "playerId": "account.0fc434bdf30b46f89710bf206982c017", "revives": 0, "rideDistance": 6066.8306, "roadKills": 0, "swimDistance": 0, "teamKills": 0, "timeSurvived": 902, "vehicleDestroys": 0, "walkDistance": 692.39, "weaponsAcquired": 4, "winPlace": 14}, "actor": "", "shardId": "steam"}}, {"type": "roster", "id": "e4e079b6-2d61-491e-a63e-9872c841f86b", "attributes": {"stats": {"rank": 5, "teamId": 14}, "won": "false", "shardId": "tournament"}, "relationships": {"team": {"data": null}, "participants": {"data": [{"type": "participant", "id": "f3dacb7f-ab50-4383-9539-625f0dde6771"}, {"type": "participant", "id": "ffa5bea1-2037-491c-9dba-94d1ef42b361"}, {"type": "participant", "id": "f4a335d9-51d4-4c41-aa05-99cc407128d5"}, {"type": "participant", "id": "40b2ee4f-a508-45da-8b06-98cf2d11defb"}]}}}, {"type": "participant", "id": "e65e95ab-a5bd-4a98-9486-ba8550fb8ed9", "attributes": {"stats": {"DBNOs": 1, "assists": 0, "boosts": 7, "damageDealt": 89.57252, "deathType": "alive", "headshotKills": 0, "heals": 5, "killPlace": 16, "killStreaks": 1, "kills": 1, "longestKill": 19.866339, "name": "NH_Nannnnn", "playerId": "account.be3c1e2f5121454abfea4b62ca13589b", "revives": 1, "rideDistance": 8584.979, "roadKills": 0, "swimDistance": 0, "teamKills": 0, "timeSurvived": 1843, "vehicleDestroys": 0, "walkDistance": 1486.777, "weaponsAcquired": 8, "winPlace": 1}, "actor": "", "shardId": "steam"}}, {"type": "participant", "id": "40b2ee4f-a508-45da-8b06-98cf2d11defb", "attributes": {"stats": {"DBNOs": 4, "assists": 2, "boosts": 6, "damageDealt": 305.76596, "deathType": "byplayer", "headshotKills": 1, "heals": 2, "killPlace": 22, "killStreaks": 1, "kills": 1, "longestKill": 55.969776, "name": "FaZe_jeemzz", "playerId": "account.a53191c1cb564946a0e1b058368ba4be", "revives": 1, "rideDistance": 3146.0369, "roadKills": 0, "swimDistance": 0, "teamKills": 0, "timeSurvived": 1364, "vehicleDestroys": 0, "walkDistance": 1065.5674, "weaponsAcquired": 7, "winPlace": 5}, "actor": "", "shardId": "steam"}}, {"type": "roster", "id": "555827e2-6778-4811-9e6c-f457074fd3a8", "attributes": {"shardId": "tournament", "stats": {"rank": 13, "teamId": 13}, "won": "false"}, "relationships": {"team": {"data": null}, "participants": {"data": [{"type": "participant", "id": "74266520-0fde-4917-9f58-2dbe148dc691"}, {"type": "participant", "id": "4b3ee294-5c2c-4053-9870-832721f397c0"}, {"type": "participant", "id": "370190bf-6c89-44b1-91ec-68354ede2ae1"}, {"type": "participant", "id": "f8de9cbf-3540-4028-8a12-197139fe0ea4"}]}}}, {"type": "participant", "id": "4dcf6b67-c44a-4aab-b9d2-15c477c5ee4c", "attributes": {"stats": {"DBNOs": 0, "assists": 0, "boosts": 2, "damageDealt": 22.819027, "deathType": "byplayer", "headshotKills": 0, "heals": 0, "killPlace": 46, "killStreaks": 0, "kills": 0, "longestKill": 0, "name": "LG_Relo", "playerId": "account.6614558d5558453080a46dbf687e7b58", "revives": 0, "rideDistance": 3974.1804, "roadKills": 0, "swimDistance": 0, "teamKills": 0, "timeSurvived": 1067, "vehicleDestroys": 0, "walkDistance": 1262.9148, "weaponsAcquired": 5, "winPlace": 9}, "actor": "", "shardId": "steam"}}, {"type": "roster", "id": "70029c33-dd89-47ce-b78d-bf74a8427d44", "attributes": {"stats": {"rank": 9, "teamId": 2}, "won": "false", "shardId": "tournament"}, "relationships": {"team": {"data": null}, "participants": {"data": [{"type": "participant", "id": "58e81669-5b88-41bf-a8ba-c70ccb285a19"}, {"type": "participant", "id": "4dcf6b67-c44a-4aab-b9d2-15c477c5ee4c"}, {"type": "participant", "id": "f2ded8eb-7500-4123-b5b2-f326fe233a2e"}, {"type": "participant", "id": "f2adef90-9f8f-4884-8f53-bedf33a29c87"}]}}}, {"type": "roster", "id": "ce4659e2-62ed-453b-873d-23c689f3b861", "attributes": {"stats": {"rank": 14, "teamId": 11}, "won": "false", "shardId": "tournament"}, "relationships": {"team": {"data": null}, "participants": {"data": [{"type": "participant", "id": "374564c8-efe7-4db6-bbd3-fe14e70f3244"}, {"type": "participant", "id": "09a46039-c0d4-4923-a8be-06abbaccb7e7"}, {"type": "participant", "id": "532a9cf0-3078-4293-adbe-69928a1fe458"}, {"type": "participant", "id": "ea9c56f7-092c-4fab-aa63-a17988879cdb"}]}}}, {"type": "participant", "id": "27b86d22-749d-4f49-b8ea-9af8ebc390ee", "attributes": {"stats": {"DBNOs": 0, "assists": 0, "boosts": 4, "damageDealt": 151.37485, "deathType": "byplayer", "headshotKills": 0, "heals": 3, "killPlace": 36, "killStreaks": 0, "kills": 0, "longestKill": 0, "name": "CES_Sololzy", "playerId": "account.1e3531b0c6db484097baa736b6ee590f", "revives": 0, "rideDistance": 8579.671, "roadKills": 0, "swimDistance": 0, "teamKills": 0, "timeSurvived": 1653, "vehicleDestroys": 1, "walkDistance": 1177.8866, "weaponsAcquired": 7, "winPlace": 2}, "actor": "", "shardId": "steam"}}, {"type": "participant", "id": "7fa34f56-434e-4d62-ad78-48342ffb731f", "attributes": {"stats": {"DBNOs": 1, "assists": 1, "boosts": 3, "damageDealt": 125.62604, "deathType": "byplayer", "headshotKills": 0, "heals": 1, "killPlace": 61, "killStreaks": 0, "kills": 0, "longestKill": 0, "name": "Tian_PaoPao", "playerId": "account.84e858daab17420e8f8b5da1a8d63fd3", "revives": 0, "rideDistance": 3054.5957, "roadKills": 0, "swimDistance": 0, "teamKills": 0, "timeSurvived": 956, "vehicleDestroys": 0, "walkDistance": 760.5672, "weaponsAcquired": 4, "winPlace": 15}, "actor": "", "shardId": "steam"}}, {"type": "participant", "id": "f3dacb7f-ab50-4383-9539-625f0dde6771", "attributes": {"stats": {"DBNOs": 2, "assists": 0, "boosts": 2, "damageDealt": 145.29744, "deathType": "byplayer", "headshotKills": 0, "heals": 3, "killPlace": 10, "killStreaks": 1, "kills": 2, "longestKill": 286.52887, "name": "FaZe_Fexx", "playerId": "account.e3c55aad6c3445678dbf4063904248ea", "revives": 0, "rideDistance": 2470.7415, "roadKills": 0, "swimDistance": 0, "teamKills": 0, "timeSurvived": 1013, "vehicleDestroys": 0, "walkDistance": 708.79553, "weaponsAcquired": 4, "winPlace": 5}, "actor": "", "shardId": "steam"}}, {"type": "participant", "id": "f4a335d9-51d4-4c41-aa05-99cc407128d5", "attributes": {"stats": {"DBNOs": 2, "assists": 3, "boosts": 3, "damageDealt": 209.55463, "deathType": "byplayer", "headshotKills": 1, "heals": 3, "killPlace": 23, "killStreaks": 1, "kills": 1, "longestKill": 192.03249, "name": "FaZe_curexi", "playerId": "account.53b4b73c4c764a26b3cc9ebd24446352", "revives": 0, "rideDistance": 3867.8574, "roadKills": 0, "swimDistance": 0, "teamKills": 0, "timeSurvived": 1321, "vehicleDestroys": 0, "walkDistance": 1202.4844, "weaponsAcquired": 7, "winPlace": 5}, "actor": "", "shardId": "steam"}}, {"type": "roster", "id": "69c37e77-dd2a-45fc-9618-a620881fe6cb", "attributes": {"stats": {"rank": 4, "teamId": 12}, "won": "false", "shardId": "tournament"}, "relationships": {"team": {"data": null}, "participants": {"data": [{"type": "participant", "id": "af531159-2e74-449c-bcde-138827554b3c"}, {"type": "participant", "id": "4fef1613-a8e7-42e9-9921-e08283144906"}, {"type": "participant", "id": "9215d4e1-d87a-4885-a091-2eaa12119039"}, {"type": "participant", "id": "ca90d0b0-13bf-438b-9668-5946a3a4b637"}]}}}, {"type": "roster", "id": "7992c390-d266-4047-a1a4-acb8f902ef7d", "attributes": {"stats": {"rank": 15, "teamId": 3}, "won": "false", "shardId": "tournament"}, "relationships": {"team": {"data": null}, "participants": {"data": [{"type": "participant", "id": "e2a8bb8c-cb51-4cdf-bff4-b74c23d2ee23"}, {"type": "participant", "id": "7fa34f56-434e-4d62-ad78-48342ffb731f"}, {"type": "participant", "id": "9b800055-0d02-4620-8250-216c823f646e"}, {"type": "participant", "id": "372eac2a-c41d-4c8f-a676-75df69f13a88"}]}}}, {"type": "asset", "id": "1e1c006e-9045-11ee-9ee4-6afa2dbf7a24", "attributes": {"name": "telemetry", "description": "", "createdAt": "2023-12-01T12:28:22Z", "URL": "https://telemetry-cdn.pubg.com/bluehole-pubg/tournament/2023/12/01/12/28/1e1c006e-9045-11ee-9ee4-6afa2dbf7a24-telemetry.json"}}], "links": {"self": "https://api-originv2.playbattlegrounds.com/shards/tournaments/matches/2e851129-46e9-423c-86cb-90610970ff19"}, "meta": {}}